isekai/__init__.py
isekai/admin.py
isekai/apps.py
isekai/extractors.py
isekai/loaders.py
isekai/miners.py
isekai/models.py
isekai/pipelines.py
isekai/seeders.py
isekai/transformers.py
isekai/types.py
isekai/contrib/__init__.py
isekai/contrib/wagtail/__init__.py
isekai/contrib/wagtail/loaders.py
isekai/contrib/wagtail/transformers.py
isekai/management/__init__.py
isekai/management/commands/__init__.py
isekai/management/commands/isekai.py
isekai/utils/__init__.py
isekai/utils/core.py
isekai/utils/graphs.py
isekai/utils/progress.py
isekai_django-0.1.0a7.dist-info/METADATA
isekai_django-0.1.0a7.dist-info/WHEEL
isekai_django-0.1.0a7.dist-info/licenses/LICENSE
isekai_django-0.1.0a7.dist-info/RECORD
