Metadata-Version: 2.4
Name: isekai-django
Version: 0.1.0a7
Summary: A Django package
Project-URL: Homepage, https://github.com/mixxorz/isekai
Project-URL: Repository, https://github.com/mixxorz/isekai
Author-email: Mitchel Cabuloy <mixxorz@gmail.com>
License-File: LICENSE
Classifier: Development Status :: 3 - Alpha
Classifier: Framework :: Django
Classifier: Framework :: Django :: 4.2
Classifier: Framework :: Django :: 5.1
Classifier: Framework :: Django :: 5.2
Classifier: Intended Audience :: Developers
Classifier: License :: OSI Approved :: MIT License
Classifier: Programming Language :: Python :: 3
Classifier: Programming Language :: Python :: 3.10
Classifier: Programming Language :: Python :: 3.11
Classifier: Programming Language :: Python :: 3.12
Classifier: Programming Language :: Python :: 3.13
Requires-Python: >=3.10
Requires-Dist: beautifulsoup4>=4.12.0
Requires-Dist: django>=4.2
Requires-Dist: requests>=2.32.5
Requires-Dist: rich>=12.0.0
Provides-Extra: wagtail
Requires-Dist: wagtail>=6.3; extra == 'wagtail'
